{"autor": "nunisse", "selo": "2021-12-04 17:56:57.320Z", "comentario": "Eu também fui nessa e noite e não te vi :(", "id_video": 2}
{"autor": "nunisse", "selo": "2021-12-04 17:56:57.229Z", "comentario": "Paulo, estás à espera do quê?", "id_video": 3}
{"autor": "nunisse", "selo": "2021-12-04 17:56:57.198Z", "comentario": "Injustiça para quem não joga setas :/", "id_video": 5}
{"autor": "joaoreis", "selo": "2021-12-04 17:56:57.161Z", "comentario": "adoro esta versão <3", "id_video": 1}
{"autor": "pylance", "selo": "2021-12-04 17:56:57.282Z", "comentario": "Epá, depois penso nisso, tenho que ir buscar a Iara ao trabalho", "id_video": 3}
{"autor": "bernoso", "selo": "2021-12-04 17:56:57.261Z", "comentario": "Papaguaio Loiro de bico doirado", "id_video": 8}
{"autor": "bernoso", "selo": "2021-12-04 17:56:57.175Z", "comentario": "Melhor do mundo <3 anda a Campia", "id_video": 10}
{"autor": "esti8", "selo": "2021-12-04 17:56:57.212Z", "comentario": "Ao tempo que não ouvia isto, saudades...", "id_video": 7}
{"autor": "serroso", "selo": "2021-12-04 17:56:57.306Z", "comentario": "@joaoreis @bernoso siga já hoje? quem perder paga os principes aos outros", "id_video": 5}
{"autor": "serroso", "selo": "2021-12-04 17:56:57.245Z", "comentario": "Riczão, sobe a dificuldade", "id_video": 6}